roastme/__init__.py
roastme/core.py
roastme-0.1.1.dist-info/licenses/LICENSE
roastme-0.1.1.dist-info/METADATA
roastme-0.1.1.dist-info/WHEEL
roastme-0.1.1.dist-info/top_level.txt
roastme-0.1.1.dist-info/RECORD
